aws_lambda_event/.DS_Store
aws_lambda_event/__init__.py
aws_lambda_event/_version.py
aws_lambda_event/base.py
aws_lambda_event/helpers.py
aws_lambda_event/__pycache__/__init__.cpython-38.pyc
aws_lambda_event/__pycache__/_version.cpython-38.pyc
aws_lambda_event/__pycache__/base.cpython-38.pyc
aws_lambda_event/__pycache__/helpers.cpython-38.pyc
aws_lambda_event/docs/__init__.py
aws_lambda_event/events/__init__.py
aws_lambda_event/events/cloudwatch_logs.py
aws_lambda_event/events/cloudwatch_scheduled_event.py
aws_lambda_event/events/dynamodb_update.py
aws_lambda_event/events/kinesis_firehose.py
aws_lambda_event/events/kinesis_stream.py
aws_lambda_event/events/s3_delete.py
aws_lambda_event/events/s3_put.py
aws_lambda_event/events/sns.py
aws_lambda_event/events/sqs.py
aws_lambda_event/events/__pycache__/__init__.cpython-38.pyc
aws_lambda_event/events/__pycache__/cloudwatch_logs.cpython-38.pyc
aws_lambda_event/events/__pycache__/cloudwatch_scheduled_event.cpython-38.pyc
aws_lambda_event/events/__pycache__/dynamodb_update.cpython-38.pyc
aws_lambda_event/events/__pycache__/kinesis_firehose.cpython-38.pyc
aws_lambda_event/events/__pycache__/kinesis_stream.cpython-38.pyc
aws_lambda_event/events/__pycache__/s3_delete.cpython-38.pyc
aws_lambda_event/events/__pycache__/s3_put.cpython-38.pyc
aws_lambda_event/events/__pycache__/sns.cpython-38.pyc
aws_lambda_event/events/__pycache__/sqs.cpython-38.pyc
aws_lambda_event-2.0.2.dist-info/AUTHORS.rst
aws_lambda_event-2.0.2.dist-info/LICENSE.txt
aws_lambda_event-2.0.2.dist-info/METADATA
aws_lambda_event-2.0.2.dist-info/WHEEL
aws_lambda_event-2.0.2.dist-info/top_level.txt
aws_lambda_event-2.0.2.dist-info/RECORD
